purrgil/__init__.py
purrgil-0.0.0.dist-info/LICENSE
purrgil-0.0.0.dist-info/METADATA
purrgil-0.0.0.dist-info/WHEEL
purrgil-0.0.0.dist-info/RECORD
